{"92": {"success": true, "data": {"screenshots": [{"path_full": "http://cdn.akamai.steamstatic.com/steam/apps/92/0000000037.1920x1080.jpg?t=1447350816", "id": 0, "path_thumbnail": "http://cdn.akamai.steamstatic.com/steam/apps/92/0000000037.600x338.jpg?t=1447350816"}, {"path_full": "http://cdn.akamai.steamstatic.com/steam/apps/92/0000000038.1920x1080.jpg?t=1447350816", "id": 1, "path_thumbnail": "http://cdn.akamai.steamstatic.com/steam/apps/92/0000000038.600x338.jpg?t=1447350816"}, {"path_full": "http://cdn.akamai.steamstatic.com/steam/apps/92/0000000039.1920x1080.jpg?t=1447350816", "id": 2, "path_thumbnail": "http://cdn.akamai.steamstatic.com/steam/apps/92/0000000039.600x338.jpg?t=1447350816"}, {"path_full": "http://cdn.akamai.steamstatic.com/steam/apps/92/0000000040.1920x1080.jpg?t=1447350816", "id": 3, "path_thumbnail": "http://cdn.akamai.steamstatic.com/steam/apps/92/0000000040.600x338.jpg?t=1447350816"}, {"path_full": "http://cdn.akamai.steamstatic.com/steam/apps/92/0000000041.1920x1080.jpg?t=1447350816", "id": 4, "path_thumbnail": "http://cdn.akamai.steamstatic.com/steam/apps/92/0000000041.600x338.jpg?t=1447350816"}], "header_image": "http://cdn.akamai.steamstatic.com/steam/apps/92/header.jpg?t=1447350816", "supported_languages": "English", "release_date": {"date": "1 May, 2004", "coming_soon": false}, "platforms": {"linux": false, "windows": true, "mac": false}, "is_free": false, "steam_appid": 92, "developers": ["Nuclear Vision"], "genres": [{"id": "23", "description": "Indie"}], "required_age": 0, "website": null, "short_description": "", "pc_requirements": [], "detailed_description": "Created by Nuclearvision Entertainment, Codename Gordon takes players through dozens of levels inspired by Half-Life and Half-Life 2, challenges players to a slew of puzzles, and showcases many of the familiar creatures in an all new, 2 dimensional playing field.", "linux_requirements": [], "support_info": {"email": "", "url": ""}, "fullgame": {"appid": null, "name": "Uninitialized"}, "name": "Codename Gordon", "publishers": ["Valve"], "package_groups": [], "mac_requirements": [], "type": "advertising", "categories": [{"id": 2, "description": "Single-player"}], "about_the_game": "Created by Nuclearvision Entertainment, Codename Gordon takes players through dozens of levels inspired by Half-Life and Half-Life 2, challenges players to a slew of puzzles, and showcases many of the familiar creatures in an all new, 2 dimensional playing field.", "background": "http://cdn.akamai.steamstatic.com/steam/apps/92/page_bg_generated_v6b.jpg?t=1447350816"}}}